prepack/__init__.py
prepack/prepack.py
preparepack-1.4.0.dist-info/METADATA
preparepack-1.4.0.dist-info/WHEEL
preparepack-1.4.0.dist-info/entry_points.txt
preparepack-1.4.0.dist-info/top_level.txt
preparepack-1.4.0.dist-info/RECORD
