Metadata-Version: 2.1
Name: preparepack
Version: 1.4.0
Summary: Prepare, build and upload Python packages
Author: Cargo
License: MIT
Platform: UNKNOWN
Requires-Dist: click
Requires-Dist: twine
